setup.py
monkit/__init__.py
monkit/monurl.py
monkit.egg-info/PKG-INFO
monkit.egg-info/SOURCES.txt
monkit.egg-info/dependency_links.txt
monkit.egg-info/entry_points.txt
monkit.egg-info/top_level.txt