Metadata-Version: 1.0
Name: monkit
Version: 0.0.4
Summary: monitor kit client
Home-page: https://github.com/pytoolkits/monkit
Author: hhr66
Author-email: hhr66@qq.com
License: MIT Licence
Keywords: monurl,monitor,monkit
Platform: any
